[
  {
    "header": {
      "headerId": "INC001",
      "title": "Initial Incident",
      "type": "Test",
      "impact": "High",
      "urgency": "High",
      "priority": "High",
      "status": "New",
      "createdTimestamp": 1627638473,
      "inProgress": false,
      "validation": false,
      "closed": false
    },
    "raci": {
      "responsibleParties": ["Team A"],
      "accountableParties": ["Manager B"],
      "consultedParties": ["Consultant C"],
      "informedParties": ["Executive D"]
    },
    "timeline": {
      "creationTimestamp": 1627638473,
      "inProgressTimestamp": 0,
      "validationTimestamp": 0,
      "closedTimestamp": 0
    },
    "documentation": {
      "description": "Initial incident description",
      "notes": "Initial incident notes"
    }
  }
]